setup.py
pstats_view.egg-info/PKG-INFO
pstats_view.egg-info/SOURCES.txt
pstats_view.egg-info/dependency_links.txt
pstats_view.egg-info/not-zip-safe
pstats_view.egg-info/requires.txt
pstats_view.egg-info/top_level.txt
pstatsviewer/__init__.py
pstatsviewer/viewer.py