Metadata-Version: 1.1
Name: pstats-view
Version: 0.1
Summary: A Graphical Viewer for CProfile Output
Home-page: https://github.com/ssanderson/pstats-view
Author: Scott Sanderson
Author-email: scoutoss@gmail.com
License: Apache 2.0
Platform: UNKNOWN
Classifier: Framework :: IPython
Classifier: Development Status :: 3 - Alpha
Classifier: License :: OSI Approved :: Apache Software License
Classifier: Natural Language :: English
Classifier: Programming Language :: Python
Classifier: Programming Language :: Python :: 2.7
Classifier: Programming Language :: Python :: 3.3
Classifier: Operating System :: OS Independent
Classifier: Intended Audience :: Science/Research
Classifier: Topic :: Office/Business :: Financial
Classifier: Topic :: Scientific/Engineering :: Information Analysis
